{"structured":{"config":{"folder":true,"fullpath":"/config/babel","name":"Config","folder_slug":"config","babel":{"page":true,"fullpath":"/config/babel","name":"Babel","page_slug":"babel"}},"docs":{"folder":true,"fullpath":"/generators/docs/aa","name":"Docs","folder_slug":"docs","generator":true,"aa":{"page":true,"fullpath":"/generators/docs/aa","name":"Aa","page_slug":"aa"},"bb":{"page":true,"fullpath":"/generators/docs/bb","name":"Bb","page_slug":"bb"},"collapsing":{"page":true,"fullpath":"/generators/docs/collapsing","name":"Collapsing","page_slug":"collapsing"}},"navigation":{"folder":true,"fullpath":"/global/navigation/mainmenu","name":"Navigation","folder_slug":"navigation","mainmenu":{"page":true,"fullpath":"/global/navigation/mainmenu","name":"Mainmenu","page_slug":"mainmenu"}},"page_setup":{"folder":true,"fullpath":"/global/page_setup/page_setup","name":"Page setup","folder_slug":"page_setup","page_setup":{"page":true,"fullpath":"/global/page_setup/page_setup","name":"Page setup","page_slug":"page_setup"}},"index":{"page":true,"fullpath":"/index","name":"Index","page_slug":"index"}},"flat":[{"page":true,"fullpath":"/config/babel","name":"Babel","page_slug":"babel"},{"page":true,"fullpath":"/generators/docs/aa","name":"Aa","page_slug":"aa"},{"page":true,"fullpath":"/generators/docs/bb","name":"Bb","page_slug":"bb"},{"page":true,"fullpath":"/generators/docs/collapsing","name":"Collapsing","page_slug":"collapsing"},{"page":true,"fullpath":"/global/navigation/mainmenu","name":"Mainmenu","page_slug":"mainmenu"},{"page":true,"fullpath":"/global/page_setup/page_setup","name":"Page setup","page_slug":"page_setup"},{"page":true,"fullpath":"/index","name":"Index","page_slug":"index"}]}